{
  "project_info": {
    "project_number": "276481583291",
    "project_id": "elemzy-teacher",
    "storage_bucket": "elemzy-teacher.appspot.com"
  },
  "client": [
    {
      "client_info": {
        "mobilesdk_app_id": "1:276481583291:android:5a679f6f8c853795bfa19e",
        "android_client_info": {
          "package_name": "com.neelkanthtandel.elemezy_teacher"
        }
      },
      "oauth_client": [
        {
          "client_id": "276481583291-0fcrl2tqggr57s0ef6ehcouid3pdap68.apps.googleusercontent.com",
          "client_type": 3
        }
      ],
      "api_key": [
        {
          "current_key": "AIzaSyDOP3cCJ4ID96TTvMsCWqbThpxobkzEASw"
        }
      ],
      "services": {
        "appinvite_service": {
          "other_platform_oauth_client": [
            {
              "client_id": "276481583291-0fcrl2tqggr57s0ef6ehcouid3pdap68.apps.googleusercontent.com",
              "client_type": 3
            }
          ]
        }
      }
    }
  ],
  "configuration_version": "1"
}